{
  "@context": "https://schema.org",
  "@type": "LocalBusiness",
  "logo": "https://res.cloudinary.com/dt3k2apqd/image/upload/q_auto/Entalpy/Logo_Entalpy_q4xaqn.png",
  "image": "/media/image_02_cropped.webp",
  "@id": "https://entalpy.no/",
  "name": "Entalpy AS",
  "slogan": "Bærekraftige varmepumper for skreddersydde løsninger – uten utslipp.",
  "address": {
    "@type": "PostalAddress",
    "streetAddress": "Langgata 38",
    "addressLocality": "Sandnes",
    "addressRegion": "Stavanger",
    "postalCode": "4306",
    "addressCountry": "Norway"
  },
  "geo": {
    "@type": "GeoCoordinates",
    "latitude": "58.852984",
    "longitude": "5.7330742"
  },
  "url": "https://entalpy.no/",
  "telephone": "+47 905 64 983",
  "email": "frank@entalpy.no",
  "founder": "Frank Utsola",
  "foundingDate": "2021",
  "keywords": "industrielle varmepumper, effektiv oppvarming, utslippsfri energi, energisparing, ELL50, ELL90",
  "makesOffer": {
    "@type": "Offer",
    "name": "Industrielle varmepumper",
    "description": "Vi tilbyr en rekke industrielle varmepumper inkludert ELL50- og ELL90-modeller. Våre varmepumper gir effektiv oppvarming, utslippsfri energi og energibesparelser."
  }
}
